AUTHORS
LICENSE
MANIFEST.in
README.rst
setup.py
acrilib/__init__.py
acrilib.egg-info/PKG-INFO
acrilib.egg-info/SOURCES.txt
acrilib.egg-info/dependency_links.txt
acrilib.egg-info/requires.txt
acrilib.egg-info/top_level.txt
acrilib/bin/__init__.py
acrilib/bin/install_required.py
acrilib/concepts/__init__.py
acrilib/concepts/find_metavar.py
acrilib/idioms/__init__.py
acrilib/idioms/complex_mapping.py
acrilib/idioms/data_types.py
acrilib/idioms/decorate.py
acrilib/idioms/digraph.py
acrilib/idioms/expandvars.py
acrilib/idioms/mediator.py
acrilib/idioms/observer.py
acrilib/idioms/osutil.py
acrilib/idioms/sequence.py
acrilib/idioms/singleton.py
acrilib/idioms/synchronize.py
acrilib/idioms/threaded.py
acrilib/logging/__init__.py
acrilib/logging/formatters.py
acrilib/logging/handlers.py
acrilib/logging/logsim.py
acrilib/setup/__init__.py
acrilib/setup/install_required.py
acrilib/setup/setup_example.py
acrilib/setup/setup_utils.py