Metadata-Version: 1.1
Name: acrilib
Version: 1.0.8
Summary: acrilib is a python library of programming patterns commonly used in Python
Home-page: https://github.com/Acrisel/acrilib
Author: Acrisel Team
Author-email: support@acrisel.com
License: MIT
Keywords: library sequence logger yield singleton thread synchronize resource pool utilities os ssh xml excel mail
Platform: UNKNOWN
Classifier: Development Status :: 5 - Production/Stable
Classifier: Environment :: Other Environment
Classifier: Intended Audience :: Developers
Classifier: License :: OSI Approved :: MIT License
Classifier: Operating System :: OS Independent
Classifier: Programming Language :: Python
Classifier: Programming Language :: Python :: 3
Classifier: Programming Language :: Python :: 3.2
Classifier: Programming Language :: Python :: 3.3
Classifier: Programming Language :: Python :: 3.4
Classifier: Programming Language :: Python :: 3.5
Classifier: Topic :: Software Development :: Libraries :: Application Frameworks
Classifier: Topic :: Software Development :: Libraries :: Python Modules
